awesometkinter/__init__.py
awesometkinter/__main__.py
awesometkinter/bidirender.py
awesometkinter/button.py
awesometkinter/config.py
awesometkinter/datepicker.py
awesometkinter/dialog.py
awesometkinter/frame.py
awesometkinter/images.py
awesometkinter/label.py
awesometkinter/menu.py
awesometkinter/progressbar.py
awesometkinter/scrollbar.py
awesometkinter/text.py
awesometkinter/tooltip.py
awesometkinter/utils.py
awesometkinter/version.py
AwesomeTkinter-2021.11.8.dist-info/LICENSE
AwesomeTkinter-2021.11.8.dist-info/METADATA
AwesomeTkinter-2021.11.8.dist-info/WHEEL
AwesomeTkinter-2021.11.8.dist-info/entry_points.txt
AwesomeTkinter-2021.11.8.dist-info/top_level.txt
AwesomeTkinter-2021.11.8.dist-info/RECORD
