Metadata-Version: 2.1
Name: AwesomeTkinter
Version: 2021.11.8
Summary: Pretty tkinter widgets
Home-page: https://github.com/Aboghazala/AwesomeTkinter
Author: Mahmoud Elshahat
Author-email: 
License: UNKNOWN
Project-URL: Source, https://github.com/Aboghazala/AwesomeTkinter
Project-URL: Tracker, https://github.com/Aboghazala/AwesomeTkinter/issues
Project-URL: Releases, https://github.com/Aboghazala/AwesomeTkinter/releases
Project-URL: Screenshots, https://github.com/Aboghazala/AwesomeTkinter/issues/1
Keywords: tkinter gui python
Platform: UNKNOWN
Classifier: Programming Language :: Python :: 3
Classifier: Programming Language :: Python :: 3.6
Classifier: Programming Language :: Python :: 3.7
Classifier: Programming Language :: Python :: 3.8
Classifier: Operating System :: OS Independent
Requires-Python: >=3.6
License-File: LICENSE
